pyseitron/__init__.py
pyseitron/auth.py
pyseitron/seitron_device.py
pyseitron/seitron_gateway.py
pyseitron/seitron_thermostat.py
pyseitron-0.0.1.dist-info/METADATA
pyseitron-0.0.1.dist-info/WHEEL
pyseitron-0.0.1.dist-info/licenses/LICENSE
pyseitron-0.0.1.dist-info/RECORD
